orthogonal/__init__.py
orthogonal/__version__.py
orthogonal/api.py
orthogonal/constants.py
orthogonal_cli-0.4.0.dist-info/METADATA
orthogonal_cli-0.4.0.dist-info/WHEEL
orthogonal_cli-0.4.0.dist-info/entry_points.txt
orthogonal_cli-0.4.0.dist-info/top_level.txt
orthogonal_cli-0.4.0.dist-info/RECORD
