Metadata-Version: 2.1
Name: orthogonal-cli
Version: 0.4.0
Summary: orthogonal-cli - CLI for the DataCrunch Tournament by CrunchDAO
Home-page: https://github.com/crunchdao/orthogonal-cli
Author: Enzo CACERES, Matteo MANZI
Author-email: enzo.caceres@crunchdao.com
Keywords: package development template
Classifier: Intended Audience :: Developers
Classifier: Programming Language :: Python :: 3.7
Requires-Python: >=3
Requires-Dist: click
Requires-Dist: requests
Requires-Dist: pandas
